nodus/__init__.py
nodus/__main__.py
nodus/db.py
nodus/job.py
nodus/manager.py
nodus/old_ui.py
nodus/ui.py
nodus/utils.py
nodus-0.1.1.dist-info/LICENSE
nodus-0.1.1.dist-info/METADATA
nodus-0.1.1.dist-info/WHEEL
nodus-0.1.1.dist-info/top_level.txt
nodus-0.1.1.dist-info/RECORD
