Metadata-Version: 2.2
Name: nodus
Version: 0.1.1
Summary: Nodus - A lightweight and reusable job manager.
Home-page: https://github.com/manuelblancovalentin/nodus
Author: Manuel Blanco Valentin
Author-email: manuel.blanco.valentin@gmail.com
Classifier: Programming Language :: Python :: 3
Classifier: License :: OSI Approved :: MIT License
Classifier: Operating System :: OS Independent
Requires-Python: >=3.7
License-File: LICENSE
Dynamic: author
Dynamic: author-email
Dynamic: classifier
Dynamic: description
Dynamic: description-content-type
Dynamic: home-page
Dynamic: requires-python
Dynamic: summary
